pollenate/__init__.py
pollenate/__main__.py
pollenate/version.py
pollenate-0.1.0.dev0.dist-info/METADATA
pollenate-0.1.0.dev0.dist-info/WHEEL
pollenate-0.1.0.dev0.dist-info/top_level.txt
pollenate-0.1.0.dev0.dist-info/RECORD
